clsp/__init__.py
clsp/clsp.py
clsp-1.4.0.dist-info/LICENSE.txt
clsp-1.4.0.dist-info/METADATA
clsp-1.4.0.dist-info/WHEEL
clsp-1.4.0.dist-info/top_level.txt
clsp-1.4.0.dist-info/RECORD
