Metadata-Version: 2.1
Name: clsp
Version: 1.4.0
Summary: CLSP short for Command Line Selection Prompt, is a by fzf inspired, minimalistic, and fast to navigate single choice prompt.
Home-page: https://github.com/DISTREAT/clsp
Author: DISTREAT
License: MIT
Keywords: python,cli,console,terminal,input,prompt,tty,ncurses,curses
Classifier: License :: OSI Approved :: MIT License
Classifier: Intended Audience :: Developers
Classifier: Environment :: Console
Classifier: Programming Language :: Python :: 3.6
Classifier: Programming Language :: Python :: 3.7
Classifier: Programming Language :: Python :: 3.8
Classifier: Programming Language :: Python :: 3.9
Classifier: Topic :: Software Development :: Libraries
Classifier: Topic :: Software Development :: User Interfaces
Classifier: Topic :: Terminals
License-File: LICENSE.txt
Requires-Dist: blessed ==1.18.0
